scripts/__init__.py
scripts/snmpv3_hashgen.py
snmpv3_hashgen/__init__.py
snmpv3_hashgen/hashgen.py
tests/__init__.py
tests/tests.py
SNMPv3_Hash_Generator-0.4.1.dist-info/LICENSE
SNMPv3_Hash_Generator-0.4.1.dist-info/METADATA
SNMPv3_Hash_Generator-0.4.1.dist-info/WHEEL
SNMPv3_Hash_Generator-0.4.1.dist-info/entry_points.txt
SNMPv3_Hash_Generator-0.4.1.dist-info/top_level.txt
SNMPv3_Hash_Generator-0.4.1.dist-info/RECORD
