Metadata-Version: 2.1
Name: SNMPv3-Hash-Generator
Version: 0.4.1
Summary: Generates SNMPv3 hashes as described in rfc3414 suitable for use with ESXi and other SNMP daemons
Home-page: https://github.com/TheMysteriousX/SNMPv3-Hash-Generator
Author: Adam Bishop
Author-email: adam@omega.org.uk
License: Apache Software License
Platform: UNKNOWN
Classifier: Development Status :: 4 - Beta
Classifier: License :: OSI Approved :: Apache Software License
Classifier: Programming Language :: Python :: 3.6
Requires-Python: >=3.6
Provides-Extra: toml
Requires-Dist: toml ; extra == 'toml'
Provides-Extra: yaml
Requires-Dist: PyYAML ; extra == 'yaml'
